{"createdAt":"2023-09-27T14:39:07.803Z","updatedAt":"2023-11-04T23:03:37.000Z","id":"553","name":"[TVHs - Job Confirmation] Candidate Confirmation","active":false,"nodes":[{"parameters":{"httpMethod":"POST","path":"candidate-confirmation","options":{"responseData":"Hẹn gặp bạn ở buổi checkin nhận việc nhé!"}},"id":"0a2056e2-6158-41ad-ab57-8b24651fa22e","name":"Webhook","type":"n8n-nodes-base.webhook","typeVersion":1,"position":[460,460],"webhookId":"7fa7d95d-3075-4639-ab81-7f0a1152380e"},{"parameters":{"method":"POST","url":"https://open.larksuite.com/open-apis/auth/v3/tenant_access_token/internal","sendBody":true,"bodyParameters":{"parameters":[{"name":"app_id","value":"cli_a59c3cab2879d010"},{"name":"app_secret","value":"2QjLBZWCdYZb6C316TYVBccENBb7EKiR"}]},"options":{}},"id":"04c6fa4c-0047-4286-9b2f-8ee919ebf24f","name":"tenant_access_token","type":"n8n-nodes-base.httpRequest","typeVersion":4.1,"position":[680,460]},{"parameters":{"method":"PUT","url":"=https://open.larksuite.com/open-apis/bitable/v1/apps/G1spbN426a5eSfsLrPalEJaNgLe/tables/tblqQTMRwVl7v7a6/records/{{ $('Webhook').item.json.query.recordID }}","sendHeaders":true,"headerParameters":{"parameters":[{"name":"Authorization","value":"=Bearer {{ $('tenant_access_token').first().json.tenant_access_token }}"}]},"sendBody":true,"specifyBody":"json","jsonBody":"{\"fields\": {\"Ứng viên xác nhận\": \"Yes\"} }","options":{}},"id":"a67a4f74-31c9-4240-9f86-603b5a9b4d7e","name":"update_candidate_confirm","type":"n8n-nodes-base.httpRequest","typeVersion":4.1,"position":[880,460]}],"connections":{"Webhook":{"main":[[{"node":"tenant_access_token","type":"main","index":0}]]},"tenant_access_token":{"main":[[{"node":"update_candidate_confirm","type":"main","index":0}]]}},"settings":{},"staticData":null,"pinData":{},"versionId":"787741cc-72cf-4f15-8bc3-c2d77f3cce31","triggerCount":1,"tags":[]}